dash_autocomplete/DashAutocomplete.py
dash_autocomplete/__init__.py
dash_autocomplete/_imports_.py
dash_autocomplete/dash_autocomplete.min.js
dash_autocomplete/dash_autocomplete.min.js.map
dash_autocomplete/metadata.json
dash_autocomplete/package-info.json
dash_autocomplete-0.1.1.dist-info/LICENSE
dash_autocomplete-0.1.1.dist-info/METADATA
dash_autocomplete-0.1.1.dist-info/WHEEL
dash_autocomplete-0.1.1.dist-info/top_level.txt
dash_autocomplete-0.1.1.dist-info/RECORD
